scrapingapi/__init__.py
scrapingapi-0.1.4.dist-info/LICENSE
scrapingapi-0.1.4.dist-info/METADATA
scrapingapi-0.1.4.dist-info/WHEEL
scrapingapi-0.1.4.dist-info/top_level.txt
scrapingapi-0.1.4.dist-info/RECORD
